mtmchinac/__init__.py
mtmchinac/base.py
mtmchinac/exception.py
mtmchinac/utils.py
mtmchinac-0.0.2.dist-info/LICENSE
mtmchinac-0.0.2.dist-info/METADATA
mtmchinac-0.0.2.dist-info/WHEEL
mtmchinac-0.0.2.dist-info/top_level.txt
mtmchinac-0.0.2.dist-info/RECORD
