Metadata-Version: 2.1
Name: mtmchinac
Version: 0.0.2
Summary: Description
License: GNU AFFERO GENERAL PUBLIC LICENSE
Classifier: Development Status :: 3 - Alpha
Classifier: Programming Language :: Python :: 3.2
Classifier: Intended Audience :: Developers
Classifier: License :: OSI Approved :: MIT License
Classifier: Operating System :: MacOS
Classifier: Operating System :: POSIX :: Linux
Classifier: Operating System :: Microsoft :: Windows
Requires-Python: >=3.6
License-File: LICENSE
Requires-Dist: requests
